HDL Lab10/traffic_light_controller.v
`timescale 1ns / 1ps

module traffic_light_controller (
    input wire clk,
    input wire reset,
    input wire ped_request,
    output reg [1:0] main_light, // 2'b10=Green, 2'b01=Yellow, 2'b00=Red
    output reg [1:0] side_light, // 2'b10=Green, 2'b01=Yellow, 2'b00=Red
    output reg walk_light        // Challenge Activity: On during side-green
);

    // Light encoding parameters
    parameter RED    = 2'b00,
              YELLOW = 2'b01,
              GREEN  = 2'b10;

    // FSM State Encoding
    parameter S_MAIN_GREEN  = 2'b00,
              S_MAIN_YELLOW = 2'b01,
              S_SIDE_GREEN  = 2'b10,
              S_SIDE_YELLOW = 2'b11;

    // Timing Intervals (in clock cycles)
    parameter TIME_MAIN_GREEN_NORMAL = 8,
              TIME_MAIN_GREEN_PED    = 3, // Shortened when ped_request is 1
              TIME_YELLOW            = 2,
              TIME_SIDE_GREEN        = 5;

    reg [1:0] state, next_state;
    reg [3:0] timer;

    // 1. Sequential State Register & Timer Counter
    always @(posedge clk or posedge reset) begin
        if (reset) begin
            state <= S_MAIN_GREEN;
            timer <= 4'd0;
        end else begin
            if (state != next_state) begin
                state <= next_state;
                timer <= 4'd0; // Reset timer on state transition
            end else begin
                timer <= timer + 1'b1;
            end
        end
    end

    // 2. Next-State Combinational Logic
    always @(*) begin
        case (state)
            S_MAIN_GREEN: begin
                // ped_request shortens main-green interval
                if (ped_request && timer >= (TIME_MAIN_GREEN_PED - 1))
                    next_state = S_MAIN_YELLOW;
                else if (timer >= (TIME_MAIN_GREEN_NORMAL - 1))
                    next_state = S_MAIN_YELLOW;
                else
                    next_state = S_MAIN_GREEN;
            end

            S_MAIN_YELLOW: begin
                if (timer >= (TIME_YELLOW - 1))
                    next_state = S_SIDE_GREEN;
                else
                    next_state = S_MAIN_YELLOW;
            end

            S_SIDE_GREEN: begin
                if (timer >= (TIME_SIDE_GREEN - 1))
                    next_state = S_SIDE_YELLOW;
                else
                    next_state = S_SIDE_GREEN;
            end

            S_SIDE_YELLOW: begin
                if (timer >= (TIME_YELLOW - 1))
                    next_state = S_MAIN_GREEN;
                else
                    next_state = S_SIDE_YELLOW;
            end

            default: next_state = S_MAIN_GREEN;
        endcase
    end

    // 3. Moore Output Logic
    always @(*) begin
        // Default outputs
        main_light = RED;
        side_light = RED;
        walk_light = 1'b0;

        case (state)
            S_MAIN_GREEN: begin
                main_light = GREEN;
                side_light = RED;
                walk_light = 1'b0;
            end

            S_MAIN_YELLOW: begin
                main_light = YELLOW;
                side_light = RED;
                walk_light = 1'b0;
            end

            S_SIDE_GREEN: begin
                main_light = RED;
                side_light = GREEN;
                walk_light = 1'b1; // Walk light turns on ONLY during side-green
            end

            S_SIDE_YELLOW: begin
                main_light = RED;
                side_light = YELLOW;
                walk_light = 1'b0;
            end

            default: begin
                main_light = RED;
                side_light = RED;
                walk_light = 1'b0;
            end
        endcase
    end

endmodule

HDL Lab10/tb_traffic_light_controller.v
`timescale 1ns / 1ps

module tb_traffic_light_controller;

    reg clk;
    reg reset;
    reg ped_request;
    wire [1:0] main_light;
    wire [1:0] side_light;
    wire walk_light;

    // Instantiate Unit Under Test (UUT)
    traffic_light_controller uut (
        .clk(clk),
        .reset(reset),
        .ped_request(ped_request),
        .main_light(main_light),
        .side_light(side_light),
        .walk_light(walk_light)
    );

    // Clock Generation (10ns period)
    always #5 clk = ~clk;

    initial begin
        // VCD Dump Setup
        $dumpfile("lab10_traffic_light.vcd");
        $dumpvars(0, tb_traffic_light_controller);

        // Initialize signals
        clk = 0;
        reset = 1;
        ped_request = 0;

        // Apply Reset
        #15 reset = 0;

        // Run full normal cycle without ped_request
        #200;

        // Assert Pedestrian Request during Main Green
        ped_request = 1;
        #20;
        ped_request = 0;

        // Finish simulation at required timestamp
        #57;
        $finish;
    end

endmodule

HDL Lab10/lab10_traffic_light.vcd
$date
	Wed Jul 29 22:49:33 2026
$end
$version
	Icarus Verilog
$end
$timescale
	1ps
$end
$scope module tb_traffic_light_controller $end
$var wire 1 ! walk_light $end
$var wire 2 " side_light [1:0] $end
$var wire 2 # main_light [1:0] $end
$var reg 1 $ clk $end
$var reg 1 % ped_request $end
$var reg 1 & reset $end
$scope module uut $end
$var wire 1 $ clk $end
$var wire 1 % ped_request $end
$var wire 1 & reset $end
$var parameter 2 ' GREEN $end
$var parameter 2 ( RED $end
$var parameter 2 ) S_MAIN_GREEN $end
$var parameter 2 * S_MAIN_YELLOW $end
$var parameter 2 + S_SIDE_GREEN $end
$var parameter 2 , S_SIDE_YELLOW $end
$var parameter 32 - TIME_MAIN_GREEN_NORMAL $end
$var parameter 32 . TIME_MAIN_GREEN_PED $end
$var parameter 32 / TIME_SIDE_GREEN $end
$var parameter 32 0 TIME_YELLOW $end
$var parameter 2 1 YELLOW $end
$var reg 2 2 main_light [1:0] $end
$var reg 2 3 next_state [1:0] $end
$var reg 2 4 side_light [1:0] $end
$var reg 2 5 state [1:0] $end
$var reg 4 6 timer [3:0] $end
$var reg 1 ! walk_light $end
$upscope $end
$upscope $end
$enddefinitions $end
$comment Show the parameter values. $end
$dumpall
b1 1
b10 0
b101 /
b11 .
b1000 -
b11 ,
b10 +
b1 *
b0 )
b0 (
b10 '
$end
#0
$dumpvars
b0 6
b0 5
b0 4
b0 3
b10 2
1&
0%
0$
b10 #
b0 "
0!
$end
#5000
1$
#10000
0$
#15000
b1 6
1$
0&
#20000
0$
#25000
b10 6
1$
#30000
0$
#35000
b11 6
1$
#40000
0$
#45000
b100 6
1$
#50000
0$
#55000
b101 6
1$
#60000
0$
#65000
b110 6
1$
#70000
0$
#75000
b1 3
b111 6
1$
#80000
0$
#85000
b1 #
b1 2
b0 6
b1 5
1$
#90000
0$
#95000
b10 3
b1 6
1$
#100000
0$
#105000
1!
b10 "
b10 4
b0 #
b0 2
b0 6
b10 5
1$
#110000
0$
#115000
b1 6
1$
#120000
0$
#125000
b10 6
1$
#130000
0$
#135000
b11 6
1$
#140000
0$
#145000
b11 3
b100 6
1$
#150000
0$
#155000
0!
b1 "
b1 4
b0 6
b11 5
1$
#160000
0$
#165000
b0 3
b1 6
1$
#170000
0$
#175000
b10 #
b10 2
b0 "
b0 4
b0 6
b0 5
1$
#180000
0$
#185000
b1 6
1$
#190000
0$
#195000
b10 6
1$
#200000
0$
#205000
b11 6
1$
#210000
0$
#215000
b1 #
b1 2
b0 6
b1 5
b1 3
1$
1%
#220000
0$
#225000
b10 3
b1 6
1$
#230000
0$
#235000
1!
b10 "
b10 4
b0 #
b0 2
b0 6
b10 5
1$
0%
#240000
0$
#245000
b1 6
1$
#250000
0$
#255000
b10 6
1$
#260000
0$
#265000
b11 6
1$
#270000
0$
#275000
b11 3
b100 6
1$
#280000
0$
#285000
0!
b1 "
b1 4
b0 6
b11 5
1$
