HDL Lab10/smart_traffic_controller.v
// Module: smart_traffic_controller
// Description: School-Zone Smart Intersection Controller with school_zone input mode

module smart_traffic_controller (
    input wire clk,
    input wire rst,
    input wire ped_request,
    input wire school_zone,     // Active high when school zone active hours are ON
    output reg [2:0] main_light, // Bit 2 = Green, Bit 1 = Yellow, Bit 0 = Red
    output reg [2:0] side_light, // Bit 2 = Green, Bit 1 = Yellow, Bit 0 = Red
    output reg ped_walk,
    output reg speed_warning    // Active high signal for school zone warning lights
);

    // State Encoding
    localparam S_MAIN_GREEN  = 3'b000;
    localparam S_MAIN_YELLOW = 3'b001;
    localparam S_PED_WALK    = 3'b010;
    localparam S_SIDE_GREEN  = 3'b011;
    localparam S_SIDE_YELLOW = 3'b100;

    // Light Encodings [G, Y, R]
    localparam LIGHT_GREEN  = 3'b100;
    localparam LIGHT_YELLOW = 3'b010;
    localparam LIGHT_RED    = 3'b001;

    // Timing Constants
    localparam TIME_MAIN_GREEN  = 5;
    localparam TIME_MAIN_YELLOW = 2;
    localparam TIME_PED_NORMAL  = 4; // Standard walk duration
    localparam TIME_PED_SCHOOL  = 8; // Extended walk duration for students
    localparam TIME_SIDE_GREEN  = 3;
    localparam TIME_SIDE_YELLOW = 2;

    reg [2:0] current_state, next_state;
    reg [3:0] timer;
    reg ped_latched;

    // 1. Pedestrian Request Latch
    always @(posedge clk or posedge rst) begin
        if (rst) begin
            ped_latched <= 1'b0;
        end else begin
            if (ped_request)
                ped_latched <= 1'b1;
            else if (current_state == S_PED_WALK)
                ped_latched <= 1'b0;
        end
    end

    // 2. Sequential State Register & Timer
    always @(posedge clk or posedge rst) begin
        if (rst) begin
            current_state <= S_MAIN_GREEN;
            timer <= 0;
        end else begin
            if (current_state != next_state) begin
                current_state <= next_state;
                timer <= 0;
            end else begin
                timer <= timer + 1'b1;
            end
        end
    end

    // 3. Next State Combinational Logic
    always @(*) begin
        next_state = current_state;
        case (current_state)
            S_MAIN_GREEN: begin
                if (timer >= TIME_MAIN_GREEN - 1 || ped_latched || ped_request)
                    next_state = S_MAIN_YELLOW;
            end

            S_MAIN_YELLOW: begin
                if (timer >= TIME_MAIN_YELLOW - 1) begin
                    if (ped_latched || ped_request)
                        next_state = S_PED_WALK;
                    else
                        next_state = S_SIDE_GREEN;
                end
            end

            S_PED_WALK: begin
                // Dynamically select walk timer threshold based on school_zone signal
                if (school_zone) begin
                    if (timer >= TIME_PED_SCHOOL - 1)
                        next_state = S_SIDE_GREEN;
                end else begin
                    if (timer >= TIME_PED_NORMAL - 1)
                        next_state = S_SIDE_GREEN;
                end
            end

            S_SIDE_GREEN: begin
                if (timer >= TIME_SIDE_GREEN - 1)
                    next_state = S_SIDE_YELLOW;
            end

            S_SIDE_YELLOW: begin
                if (timer >= TIME_SIDE_YELLOW - 1)
                    next_state = S_MAIN_GREEN;
            end

            default: next_state = S_MAIN_GREEN;
        endcase
    end

    // 4. Output Combinational Logic
    always @(*) begin
        main_light    = LIGHT_RED;
        side_light    = LIGHT_RED;
        ped_walk      = 1'b0;
        speed_warning = school_zone; // Speed warning active whenever school_zone=1

        case (current_state)
            S_MAIN_GREEN: begin
                main_light = LIGHT_GREEN;
                side_light = LIGHT_RED;
                ped_walk   = 1'b0;
            end
            S_MAIN_YELLOW: begin
                main_light = LIGHT_YELLOW;
                side_light = LIGHT_RED;
                ped_walk   = 1'b0;
            end
            S_PED_WALK: begin
                main_light = LIGHT_RED;
                side_light = LIGHT_RED;
                ped_walk   = 1'b1;
            end
            S_SIDE_GREEN: begin
                main_light = LIGHT_RED;
                side_light = LIGHT_GREEN;
                ped_walk   = 1'b0;
            end
            S_SIDE_YELLOW: begin
                main_light = LIGHT_RED;
                side_light = LIGHT_YELLOW;
                ped_walk   = 1'b0;
            end
        endcase
    end

endmodule

HDL Lab10/tb_smart_traffic_controller.v
`timescale 1ns / 1ps

module tb_smart_traffic_controller();

    reg clk;
    reg rst;
    reg ped_request;
    reg school_zone;

    wire [2:0] main_light;
    wire [2:0] side_light;
    wire ped_walk;
    wire speed_warning;

    smart_traffic_controller uut (
        .clk(clk),
        .rst(rst),
        .ped_request(ped_request),
        .school_zone(school_zone),
        .main_light(main_light),
        .side_light(side_light),
        .ped_walk(ped_walk),
        .speed_warning(speed_warning)
    );

    // 10ns Clock Period
    always #5 clk = ~clk;

    initial begin
        $dumpfile("traffic_sim.vcd");
        $dumpvars(0, tb_smart_traffic_controller);

        clk = 0;
        rst = 0;
        ped_request = 0;
        school_zone = 0;

        // TC1: Reset
        $display("=== TC1: System Reset ===");
        #2 rst = 1;
        #10 rst = 0;

        // TC2: Normal Operation (No School Zone)
        $display("=== TC2: Standard Cycle ===");
        #160;

        // TC3: Pedestrian Request during Normal Mode (Walk = 4 Cycles)
        $display("=== TC3: Pedestrian Request (Standard Mode) ===");
        #10 ped_request = 1;
        #10 ped_request = 0;
        #100;

        // TC4: Activate School Zone Mode (Walk = 8 Cycles + Speed Warning ON)
        $display("=== TC4: Activating School Zone Mode ===");
        school_zone = 1;
        #20;
        ped_request = 1;
        #10 ped_request = 0;
        #160;

        // TC5: Reset during Active School Zone Walk Phase (Edge Case)
        $display("=== TC5: Edge Case - Reset during Active Pedestrian Phase ===");
        #10 ped_request = 1;
        #10 ped_request = 0;
        #25;
        rst = 1;
        #10 rst = 0;
        #60;

        $display("=== Simulation Finished ===");
        $finish;
    end

    initial begin
        $monitor("[Time %0t ns] State: Main=%b | Side=%b | Ped_Walk=%b | SchoolZone=%b | Warning=%b", 
                 $time, main_light, side_light, ped_walk, school_zone, speed_warning);
    end

endmodule

HDL Lab10/traffic_sim.vcd
$date
	Wed Jul 29 23:01:49 2026
$end
$version
	Icarus Verilog
$end
$timescale
	1ps
$end
$scope module tb_smart_traffic_controller $end
$var wire 1 ! speed_warning $end
$var wire 3 " side_light [2:0] $end
$var wire 1 # ped_walk $end
$var wire 3 $ main_light [2:0] $end
$var reg 1 % clk $end
$var reg 1 & ped_request $end
$var reg 1 ' rst $end
$var reg 1 ( school_zone $end
$scope module uut $end
$var wire 1 % clk $end
$var wire 1 & ped_request $end
$var wire 1 ' rst $end
$var wire 1 ( school_zone $end
$var parameter 3 ) LIGHT_GREEN $end
$var parameter 3 * LIGHT_RED $end
$var parameter 3 + LIGHT_YELLOW $end
$var parameter 3 , S_MAIN_GREEN $end
$var parameter 3 - S_MAIN_YELLOW $end
$var parameter 3 . S_PED_WALK $end
$var parameter 3 / S_SIDE_GREEN $end
$var parameter 3 0 S_SIDE_YELLOW $end
$var parameter 32 1 TIME_MAIN_GREEN $end
$var parameter 32 2 TIME_MAIN_YELLOW $end
$var parameter 32 3 TIME_PED_NORMAL $end
$var parameter 32 4 TIME_PED_SCHOOL $end
$var parameter 32 5 TIME_SIDE_GREEN $end
$var parameter 32 6 TIME_SIDE_YELLOW $end
$var reg 3 7 current_state [2:0] $end
$var reg 3 8 main_light [2:0] $end
$var reg 3 9 next_state [2:0] $end
$var reg 1 : ped_latched $end
$var reg 1 # ped_walk $end
$var reg 3 ; side_light [2:0] $end
$var reg 1 ! speed_warning $end
$var reg 4 < timer [3:0] $end
$upscope $end
$upscope $end
$enddefinitions $end
$comment Show the parameter values. $end
$dumpall
b10 6
b11 5
b1000 4
b100 3
b10 2
b101 1
b100 0
b11 /
b10 .
b1 -
b0 ,
b10 +
b1 *
b100 )
$end
#0
$dumpvars
bx <
b1 ;
x:
b0 9
b1 8
bx 7
0(
0'
0&
0%
b1 $
0#
b1 "
0!
$end
#2000
b100 $
b100 8
0:
b0 <
b0 7
1'
#5000
1%
#10000
0%
#12000
0'
#15000
b1 <
1%
#20000
0%
#25000
b10 <
1%
#30000
0%
#35000
b11 <
1%
#40000
0%
#45000
b1 9
b100 <
1%
#50000
0%
#55000
b10 $
b10 8
b0 <
b1 7
1%
#60000
0%
#65000
b11 9
b1 <
1%
#70000
0%
#75000
b100 "
b100 ;
b1 $
b1 8
b0 <
b11 7
1%
#80000
0%
#85000
b1 <
1%
#90000
0%
#95000
b100 9
b10 <
1%
#100000
0%
#105000
b10 "
b10 ;
b0 <
b100 7
1%
#110000
0%
#115000
b0 9
b1 <
1%
#120000
0%
#125000
b100 $
b100 8
b1 "
b1 ;
b0 <
b0 7
1%
#130000
0%
#135000
b1 <
1%
#140000
0%
#145000
b10 <
1%
#150000
0%
#155000
b11 <
1%
#160000
0%
#165000
b1 9
b100 <
1%
#170000
0%
#175000
b10 $
b10 8
b0 <
b1 7
1%
#180000
0%
#182000
1&
#185000
b10 9
b1 <
1:
1%
#190000
0%
#192000
b10 9
0&
#195000
1#
b1 $
b1 8
b0 <
b10 7
1%
#200000
0%
#205000
b1 <
0:
1%
#210000
0%
#215000
b10 <
1%
#220000
0%
#225000
b11 9
b11 <
1%
#230000
0%
#235000
b100 "
b100 ;
0#
b0 <
b11 7
1%
#240000
0%
#245000
b1 <
1%
#250000
0%
#255000
b100 9
b10 <
1%
#260000
0%
#265000
b10 "
b10 ;
b0 <
b100 7
1%
#270000
0%
#275000
b0 9
b1 <
1%
#280000
0%
#285000
b100 $
b100 8
b1 "
b1 ;
b0 <
b0 7
1%
#290000
0%
#292000
1!
b100 $
b100 8
1(
#295000
b1 <
1%
#300000
0%
#305000
b10 <
1%
#310000
0%
#312000
b1 9
1&
#315000
b10 $
b10 8
1:
b0 <
b1 7
1%
#320000
0%
#322000
0&
#325000
b10 9
b1 <
1%
#330000
0%
#335000
1#
b1 $
b1 8
b0 <
b10 7
1%
#340000
0%
#345000
b1 <
0:
1%
#350000
0%
#355000
b10 <
1%
#360000
0%
#365000
b11 <
1%
#370000
0%
#375000
b100 <
1%
#380000
0%
#385000
b101 <
1%
#390000
0%
#395000
b110 <
1%
#400000
0%
#405000
b11 9
b111 <
1%
#410000
0%
#415000
b100 "
b100 ;
0#
b0 <
b11 7
1%
#420000
0%
#425000
b1 <
1%
#430000
0%
#435000
b100 9
b10 <
1%
#440000
0%
#445000
b10 "
b10 ;
b0 <
b100 7
1%
#450000
0%
#455000
b0 9
b1 <
1%
#460000
0%
#465000
b100 $
b100 8
b1 "
b1 ;
b0 <
b0 7
1%
#470000
0%
#475000
b1 <
1%
#480000
0%
#485000
b10 <
1%
#490000
0%
#492000
b1 9
1&
#495000
b10 $
b10 8
1:
b0 <
b1 7
1%
#500000
0%
#502000
0&
#505000
b10 9
b1 <
1%
#510000
0%
#515000
1#
b1 $
b1 8
b0 <
b10 7
1%
#520000
0%
#525000
b1 <
0:
1%
#527000
b100 $
b100 8
0#
b0 9
b0 <
b0 7
1'
#530000
0%
#535000
1%
#537000
0'
#540000
0%
#545000
b1 <
1%
#550000
0%
#555000
b10 <
1%
#560000
0%
#565000
b11 <
1%
#570000
0%
#575000
b1 9
b100 <
1%
#580000
0%
#585000
b10 $
b10 8
b0 <
b1 7
1%
#590000
0%
#595000
b11 9
b1 <
1%
